zspell-0.5.5.dist-info/METADATA
zspell-0.5.5.dist-info/WHEEL
zspell-0.5.5.dist-info/license_files/LICENSE
zspell/__init__.py
zspell/zspell.cpython-312-darwin.so
zspell-0.5.5.dist-info/RECORD
