Metadata-Version: 2.1
Name: zspell
Version: 0.5.5
Classifier: Programming Language :: Rust
Classifier: Programming Language :: Python :: Implementation :: CPython
Classifier: Programming Language :: Python :: Implementation :: PyPy
License-File: LICENSE
Summary: A simple yet fast spellchecker that works with Hunspell dictionaries
Requires-Python: >=3.7
